django_flat_json_widget-0.4.dist-info/licenses/LICENSE
flat_json_widget/__init__.py
flat_json_widget/tests.py
flat_json_widget/widgets.py
flat_json_widget/static/flat-json-widget/css/flat-json-widget.css
flat_json_widget/static/flat-json-widget/js/flat-json-widget.js
flat_json_widget/static/flat-json-widget/js/lib/underscore-umd-min.js
flat_json_widget/templates/flat_json_widget/flat_json_widget.html
django_flat_json_widget-0.4.dist-info/METADATA
django_flat_json_widget-0.4.dist-info/WHEEL
django_flat_json_widget-0.4.dist-info/top_level.txt
django_flat_json_widget-0.4.dist-info/RECORD
