Metadata-Version: 2.4
Name: django-flat-json-widget
Version: 0.4
Summary: Django Flat JSON Key/Value Widget
Home-page: https://github.com/openwisp/django-flat-json-widget
Download-URL: https://github.com/openwisp/django-flat-json-widget/releases
Author: OpenWISP
Author-email: support@openwisp.io
License: BSD-3-Clause
Keywords: django,json,key-value,widget
Platform: Platform Independent
Classifier: Development Status :: 5 - Production/Stable
Classifier: Environment :: Web Environment
Classifier: Topic :: Internet :: WWW/HTTP
Classifier: Intended Audience :: Developers
Classifier: License :: OSI Approved :: BSD License
Classifier: Operating System :: OS Independent
Classifier: Framework :: Django
Classifier: Framework :: Django :: 4.2
Classifier: Framework :: Django :: 5.1
Classifier: Framework :: Django :: 5.2
Classifier: Programming Language :: Python :: 3
Classifier: Programming Language :: Python :: 3.9
Classifier: Programming Language :: Python :: 3.10
Classifier: Programming Language :: Python :: 3.11
Classifier: Programming Language :: Python :: 3.12
Classifier: Programming Language :: Python :: 3.13
Requires-Python: >=3.9
License-File: LICENSE
Requires-Dist: django<5.3,>=4.2
Provides-Extra: test
Requires-Dist: openwisp-utils[qa,selenium]~=1.2.0; extra == "test"
Requires-Dist: django-extensions<4.2,>=3.2; extra == "test"
Dynamic: author
Dynamic: author-email
Dynamic: classifier
Dynamic: description
Dynamic: download-url
Dynamic: home-page
Dynamic: keywords
Dynamic: license
Dynamic: license-file
Dynamic: platform
Dynamic: provides-extra
Dynamic: requires-dist
Dynamic: requires-python
Dynamic: summary
